bluma/__init__.py
bluma/client.py
bluma/errors.py
bluma/types.py
bluma/webhooks.py
bluma-1.2.0.dist-info/licenses/LICENSE
bluma-1.2.0.dist-info/METADATA
bluma-1.2.0.dist-info/WHEEL
bluma-1.2.0.dist-info/top_level.txt
bluma-1.2.0.dist-info/RECORD
