Metadata-Version: 2.4
Name: bluma
Version: 1.2.0
Summary: Official Python SDK for the Bluma API
Author-email: Bluma <sdk@bluma.app>
License: MIT
Project-URL: Homepage, https://bluma.app
Project-URL: Documentation, https://docs.bluma.app
Project-URL: Repository, https://github.com/bluma/bluma-python
Project-URL: Issues, https://github.com/bluma/bluma-python/issues
Keywords: bluma,video,ai,sdk,api-client
Classifier: Development Status :: 4 - Beta
Classifier: Intended Audience :: Developers
Classifier: License :: OSI Approved :: MIT License
Classifier: Programming Language :: Python :: 3
Classifier: Programming Language :: Python :: 3.8
Classifier: Programming Language :: Python :: 3.9
Classifier: Programming Language :: Python :: 3.10
Classifier: Programming Language :: Python :: 3.11
Classifier: Programming Language :: Python :: 3.12
Classifier: Typing :: Typed
Requires-Python: >=3.8
License-File: LICENSE
Requires-Dist: httpx>=0.27.0
Requires-Dist: pydantic>=2.0.0
Provides-Extra: async
Provides-Extra: dev
Requires-Dist: pytest>=8.0.0; extra == "dev"
Requires-Dist: pytest-asyncio>=0.23.0; extra == "dev"
Requires-Dist: pytest-httpx>=0.30.0; extra == "dev"
Requires-Dist: pytest-cov>=4.0.0; extra == "dev"
Requires-Dist: python-dotenv>=1.0.0; extra == "dev"
Requires-Dist: black>=24.0.0; extra == "dev"
Requires-Dist: mypy>=1.8.0; extra == "dev"
Requires-Dist: ruff>=0.2.0; extra == "dev"
Dynamic: license-file
